braillert/__init__.py
braillert/colors.py
braillert/exceptions.py
braillert/generator.py
braillert/logger.py
braillert/logo.ansi
braillert/main.py
braillert-2.1.7.dist-info/LICENSE
braillert-2.1.7.dist-info/METADATA
braillert-2.1.7.dist-info/WHEEL
braillert-2.1.7.dist-info/entry_points.txt
braillert-2.1.7.dist-info/top_level.txt
braillert-2.1.7.dist-info/RECORD
