Metadata-Version: 2.1
Name: braillert
Version: 2.1.7
Home-page: https://github.com/ov3rwrite/braillert
Author: ov3rwrite
Author-email: ilyabelykh123@gmail.com
License: MIT
License-File: LICENSE
Requires-Dist: pillow (~=9.1.1)
